simbricks/utils/__init__.py
simbricks/utils/artifatcs.py
simbricks/utils/base.py
simbricks/utils/file.py
simbricks/utils/graphlib.py
simbricks/utils/load_mod.py
simbricks_utils-0.3.6.dist-info/METADATA
simbricks_utils-0.3.6.dist-info/WHEEL
simbricks_utils-0.3.6.dist-info/RECORD
